MANIFEST.in
README.rst
setup.py
interlegis/__init__.py
interlegis.recipe.sapl.egg-info/PKG-INFO
interlegis.recipe.sapl.egg-info/SOURCES.txt
interlegis.recipe.sapl.egg-info/dependency_links.txt
interlegis.recipe.sapl.egg-info/entry_points.txt
interlegis.recipe.sapl.egg-info/namespace_packages.txt
interlegis.recipe.sapl.egg-info/not-zip-safe
interlegis.recipe.sapl.egg-info/requires.txt
interlegis.recipe.sapl.egg-info/top_level.txt
interlegis/recipe/__init__.py
interlegis/recipe/sapl/__init__.py
interlegis/recipe/sapl/sapl.py