Metadata-Version: 1.1
Name: interlegis.recipe.sapl
Version: 1.0a3
Summary: Recipe to create SAPL as part of a buildout run
Home-page: https://github.com/interlegis/interlegis.recipe.sapl
Author: Gustavo Lepri
Author-email: gustavolepri@gmail.com
License: ZPL
Keywords: sapl interlegis buildout recipe
Platform: UNKNOWN
Classifier: Framework :: Buildout
Classifier: Intended Audience :: Developers
Classifier: Topic :: Software Development :: Build Tools
Classifier: Topic :: Software Development :: Libraries :: Python Modules
Classifier: License :: OSI Approved :: Zope Public License
